axel/__init__.py
axel/axel.py
axel-0.0.7.dist-info/DESCRIPTION.rst
axel-0.0.7.dist-info/METADATA
axel-0.0.7.dist-info/RECORD
axel-0.0.7.dist-info/WHEEL
axel-0.0.7.dist-info/metadata.json
axel-0.0.7.dist-info/top_level.txt
