Metadata-Version: 2.0
Name: axel
Version: 0.0.7
Summary: Python events handling, C# style
Home-page: https://github.com/axel-events/axel
Author: Adrian Cristea
Author-email: adrian.cristea@gmail.com 
License: MIT
Keywords: event raise handle
Platform: UNKNOWN
Classifier: Development Status :: 4 - Beta
Classifier: Intended Audience :: Developers
Classifier: License :: OSI Approved :: MIT License
Classifier: Operating System :: OS Independent
Classifier: Programming Language :: Python :: 2
Classifier: Programming Language :: Python :: 3
Classifier: Topic :: Software Development :: Libraries :: Python Modules
Classifier: Topic :: Utilities
